flowerpower/__init__.py
flowerpower/flowerpower.py
flowerpower/cfg/__init__.py
flowerpower/cfg/base.py
flowerpower/cfg/exceptions.py
flowerpower/cfg/pipeline/__init__.py
flowerpower/cfg/pipeline/adapter.py
flowerpower/cfg/pipeline/builder.py
flowerpower/cfg/pipeline/builder_adapter.py
flowerpower/cfg/pipeline/builder_executor.py
flowerpower/cfg/pipeline/run.py
flowerpower/cfg/project/__init__.py
flowerpower/cfg/project/adapter.py
flowerpower/cli/__init__.py
flowerpower/cli/cfg.py
flowerpower/cli/pipeline.py
flowerpower/cli/utils.py
flowerpower/pipeline/__init__.py
flowerpower/pipeline/base.py
flowerpower/pipeline/config_manager.py
flowerpower/pipeline/execution_context.py
flowerpower/pipeline/executor.py
flowerpower/pipeline/io.py
flowerpower/pipeline/lifecycle_manager.py
flowerpower/pipeline/manager.py
flowerpower/pipeline/pipeline.py
flowerpower/pipeline/registry.py
flowerpower/pipeline/retry.py
flowerpower/pipeline/runner.py
flowerpower/pipeline/telemetry.py
flowerpower/pipeline/visualizer.py
flowerpower/plugins/io/__init__.py
flowerpower/settings/__init__.py
flowerpower/settings/executor.py
flowerpower/settings/general.py
flowerpower/settings/hamilton.py
flowerpower/settings/logging.py
flowerpower/settings/retry.py
flowerpower/utils/__init__.py
flowerpower/utils/adapter.py
flowerpower/utils/callback.py
flowerpower/utils/config.py
flowerpower/utils/env.py
flowerpower/utils/executor.py
flowerpower/utils/filesystem.py
flowerpower/utils/logging.py
flowerpower/utils/misc.py
flowerpower/utils/open_telemetry.py
flowerpower/utils/security.py
flowerpower/utils/templates.py
flowerpower/utils/yaml_env.py
flowerpower-0.34.1.dist-info/licenses/LICENSE
flowerpower-0.34.1.dist-info/METADATA
flowerpower-0.34.1.dist-info/WHEEL
flowerpower-0.34.1.dist-info/entry_points.txt
flowerpower-0.34.1.dist-info/top_level.txt
flowerpower-0.34.1.dist-info/RECORD
