Metadata-Version: 2.4
Name: FlowerPower
Version: 0.34.1
Summary: A simple workflow framework for building and managing data processing pipelines
Author-email: "Volker L." <ligno.blades@gmail.com>
Project-URL: Homepage, https://github.com/legout/flowerpower
Project-URL: Bug Tracker, https://github.com/legout/flowerpower/issues
Keywords: hamilton,workflow,pipeline,scheduler,dask,ray
Requires-Python: >=3.11
License-File: LICENSE
Requires-Dist: duration-parser>=1.0.1
Requires-Dist: fsspec>=2024.10.0
Requires-Dist: fsspeckit>=0.1.0
Requires-Dist: humanize>=4.12.2
Requires-Dist: msgspec>=0.19.0
Requires-Dist: munch>=4.0.0
Requires-Dist: pyyaml>=6.0.1
Requires-Dist: rich>=13.9.3
Requires-Dist: s3fs>=2024.10.0
Requires-Dist: sf-hamilton-sdk>=0.5.2
Requires-Dist: sf-hamilton[rich,tqdm,visualization]>=1.69.0
Requires-Dist: typer>=0.12.3
Provides-Extra: io
Requires-Dist: flowerpower-io>=0.1.1; extra == "io"
Provides-Extra: io-legacy
Requires-Dist: flowerpower-io[legacy]>=0.1.1; extra == "io-legacy"
Provides-Extra: opentelemetry
Requires-Dist: opentelemetry-api>=1.5.0; extra == "opentelemetry"
Requires-Dist: opentelemetry-sdk>=1.5.0; extra == "opentelemetry"
Requires-Dist: opentelemetry-exporter-jaeger>=1.21.0; extra == "opentelemetry"
Provides-Extra: ray
Requires-Dist: ray>=2.34.0; extra == "ray"
Provides-Extra: ui
Requires-Dist: sf-hamilton-ui>=0.0.11; extra == "ui"
Provides-Extra: openlineage
Requires-Dist: openlineage-python>=1.32.0; extra == "openlineage"
Dynamic: license-file
